setup.py
sitecustomize.py
reckless/1DDi.py
reckless/__init__.py
reckless/execute.py
reckless.egg-info/PKG-INFO
reckless.egg-info/SOURCES.txt
reckless.egg-info/dependency_links.txt
reckless.egg-info/not-zip-safe
reckless.egg-info/requires.txt
reckless.egg-info/top_level.txt