Metadata-Version: 1.1
Name: reckless
Version: 0.3
Summary: An exception hook that can keep running code after a top-level exception occurs
Home-page: UNKNOWN
Author: Ed Kellett
Author-email: edk141@gmail.com
License: MIT
Platform: UNKNOWN
Classifier: Development Status :: 2 - Pre-Alpha
Classifier: Environment :: Console
Classifier: Intended Audience :: Developers
Classifier: License :: OSI Approved :: MIT License
Classifier: Operating System :: OS Independent
Classifier: Programming Language :: Python :: 2.7
Classifier: Programming Language :: Python :: Implementation :: CPython
Classifier: Topic :: Software Development :: Debuggers
Classifier: Topic :: Utilities
